integration_sdk_orkendeu_mis/__init__.py
integration_sdk_orkendeu_mis/config.py
integration_sdk_orkendeu_mis/main.py
integration_sdk_orkendeu_mis/settings.py
integration_sdk_orkendeu_mis/utils.py
integration_sdk_orkendeu_mis/data_subjects/__init__.py
integration_sdk_orkendeu_mis/data_subjects/abstract.py
integration_sdk_orkendeu_mis/data_subjects/schema.py
integration_sdk_orkendeu_mis/data_subjects/mixins/__init__.py
integration_sdk_orkendeu_mis/data_subjects/mixins/cache_logging.py
integration_sdk_orkendeu_mis/data_subjects/mixins/error_handling.py
integration_sdk_orkendeu_mis/fetchers/__init__.py
integration_sdk_orkendeu_mis/fetchers/abstract.py
integration_sdk_orkendeu_mis/fetchers/sync_rest.py
integration_sdk_orkendeu_mis/fetchers/sync_soap.py
integration_sdk_orkendeu_mis/fetchers/mixins/__init__.py
integration_sdk_orkendeu_mis/fetchers/mixins/auth_mixin.py
integration_sdk_orkendeu_mis/fetchers/mixins/cache_mixin.py
integration_sdk_orkendeu_mis/fetchers/mixins/retry_mixin.py
integration_sdk_orkendeu_mis/handlers/__init__.py
integration_sdk_orkendeu_mis/handlers/abstract.py
integration_sdk_orkendeu_mis/handlers/dto/__init__.py
integration_sdk_orkendeu_mis/handlers/dto/handler_result_dto.py
integration_sdk_orkendeu_mis/handlers/mixins/__init__.py
integration_sdk_orkendeu_mis/handlers/mixins/trace_logging.py
integration_sdk_orkendeu_mis/handlers/mixins/validation.py
integration_sdk_orkendeu_mis/parsers/__init__.py
integration_sdk_orkendeu_mis/parsers/abstract.py
integration_sdk_orkendeu_mis/parsers/json_parser.py
integration_sdk_orkendeu_mis/parsers/mixins/__init__.py
integration_sdk_orkendeu_mis/parsers/mixins/error_check.py
integration_sdk_orkendeu_mis/parsers/mixins/xml_utils.py
integration_sdk_orkendeu_mis/providers/__init__.py
integration_sdk_orkendeu_mis/providers/abstract.py
integration_sdk_orkendeu_mis/providers/presets/__init__.py
integration_sdk_orkendeu_mis/providers/presets/common_params.py
integration_sdk_orkendeu_mis/tests/__init__.py
src/__init__.py
integration_sdk_orkendeu_mis-0.1.4.dist-info/METADATA
integration_sdk_orkendeu_mis-0.1.4.dist-info/WHEEL
integration_sdk_orkendeu_mis-0.1.4.dist-info/top_level.txt
integration_sdk_orkendeu_mis-0.1.4.dist-info/RECORD
