Metadata-Version: 2.4
Name: integration_sdk_orkendeu_mis
Version: 0.1.4
Summary: Integration SDK for external service integration (eGov, SOAP, REST)
Home-page: https://code.nkz.icdc.io/job.anvarbek/base-integration-sdk-orkendeu-project
Author: Anvarbek
Classifier: Programming Language :: Python :: 3
Classifier: License :: OSI Approved :: MIT License
Classifier: Operating System :: OS Independent
Requires-Python: >=3.10
Requires-Dist: fastapi
Requires-Dist: pydantic
Requires-Dist: httpx
Requires-Dist: lxml
Requires-Dist: tenacity
Requires-Dist: redis
Requires-Dist: uvicorn
Requires-Dist: pytest
Requires-Dist: aioredis
Dynamic: requires-dist
